jh_utils/__init__.py
jh_utils/data/__init__.py
jh_utils/data/sql/__init__.py
jh_utils/data/sql/connection.py
jh_utils/data/sql/manipulate_db.py
jh_utils/data/sql/migration.py
jh_utils/data/sql/object.py
jh_utils/ml/__init__.py
jh_utils/ml/time_series/__init__.py
jh_utils/ml/time_series/covariables.py
jh_utils/ml/time_series/plots.py
jh_utils/ml/time_series/random.py
jh_utils/ml/time_series/time_dataframe.py
jh_utils/utils/__init__.py
jh_utils/utils/hide.py
jh_utils/utils/log.py
jh_utils/utils/mensages.py
jh_utils/utils/os.py
jh_utils/utils/regex.py
jh_utils/utils/time.py
jh_utils/utils/utils.py
jh_utils-0.1.54.dist-info/licenses/LICENSE.txt
jh_utils-0.1.54.dist-info/METADATA
jh_utils-0.1.54.dist-info/WHEEL
jh_utils-0.1.54.dist-info/top_level.txt
jh_utils-0.1.54.dist-info/RECORD
