Metadata-Version: 2.4
Name: jh_utils
Version: 0.1.54
Summary: Some simple functions to all projects
Home-page: https://github.com/JohnHolz/jh_utils
Author: joao holz
Author-email: joaopaulo.paivaholz@gmail.com
License: MIT
Classifier: License :: OSI Approved :: MIT License
Classifier: Programming Language :: Python
Classifier: Programming Language :: Python :: 3.7
License-File: LICENSE.txt
Requires-Dist: python-dotenv>=0.19.0
Requires-Dist: requests>=2.26.0
Requires-Dist: pandas>=1.3.3
Requires-Dist: numpy>=1.21.2
Requires-Dist: psycopg2-binary>=2.9.1
Requires-Dist: sqlalchemy>=1.4.22
Dynamic: author
Dynamic: author-email
Dynamic: classifier
Dynamic: description
Dynamic: description-content-type
Dynamic: home-page
Dynamic: license
Dynamic: license-file
Dynamic: requires-dist
Dynamic: summary
